[
  {
    "id": "01",
    "moment": "",
    "message": "Breathe deeply, and remind yourself that this moment is temporary. Focus on the present, not the worries of tomorrow.",
    "length": "45 secs",
    "gift": "A hot meal at Indigos Restaurant",
    "recipient": "Tyler",
    "name": "Sarah",
    "phone": "780383633",
    "timestamp": 1654254000000
  },
  {
    "id": "02",
    "message": "It's okay to not have it all figured out. Be gentle with yourself, and take one small step at a time.",
    "length": "20 secs",
    "recipient": "Tyler",
    "name": "Sarah",
    "phone": "780383633",
    "timestamp": 173368335893
  },
  {
    "id": "03",
    "message": "You are stronger than you think, and every effort you make to care for yourself is a victory.",
    "length": "15 secs",
    "recipient": "Tyler",
    "name": "Sarah",
    "phone": "780383633",
    "timestamp": 173368335893
  },
  {
    "id": "04",
    "message": "Notice the small things: the warmth of sunlight, the rhythm of your breath, or the quiet moments of peace",
    "length": "25 secs",
    "recipient": "Tyler",
    "name": "Sarah",
    "phone": "780383633",
    "timestamp": 173368335893
  },
  {
    "id": "05",
    "message": "You are allowed to pause. It's not about moving fast, but moving forward at your own pace.",
    "length": "60 secs",
    "recipient": "Tyler",
    "name": "Sarah",
    "phone": "780383633",
    "timestamp": 173368335893
  },
  {
    "id": "f1540e9d-5f79-49da-8f3b-de862f1bb614",
    "message": "Notice the small things: the warmth of sunlight, the rhythm of your breath, or the quiet moments of peace",
    "length": "25 secs",
    "recipient": "Sade",
    "phone": "7803820633",
    "timestamp": 1729287419074
  },
  {
    "id": "d7d30f37-2b29-41f1-963e-6a6a3c6c9628",
    "name": "Brie",
    "message": "Notice the small things: the warmth of sunlight, the rhythm of your breath, or the quiet moments of peace",
    "length": "25 secs",
    "recipient": "Sade",
    "phone": "7803820634",
    "timestamp": 1729287486152
  }
]
